littlegrad/__init__.py
littlegrad/models_eqx.py
littlegrad/scorenet.py
littlegrad-0.0.7.dist-info/METADATA
littlegrad-0.0.7.dist-info/WHEEL
littlegrad-0.0.7.dist-info/top_level.txt
littlegrad-0.0.7.dist-info/RECORD
